{"cameraMode":{"drawMode":0,"name":"Shaded","section":"Shading Mode"},"sceneLighting":true,"audioPlay":false,"sceneViewState":{"m_AlwaysRefresh":false,"showFog":false,"showSkybox":false,"showFlares":false,"showImageEffects":false,"showParticleSystems":false,"showVisualEffectGraphs":false,"m_FxEnabled":true},"in2DMode":false,"pivot":{"x":-5.05499792098999,"y":2.348801374435425,"z":23.491008758544923},"rotation":{"x":0.14299610257148744,"y":0.26121971011161806,"z":-0.03916093707084656,"w":0.9538280963897705},"size":2.0179009437561037,"orthographic":false}